xmlhtml2pandas/README.MD
xmlhtml2pandas/__init__.py
xmlhtml2pandas/requirements.txt
xmlhtml2pandas/thirdparty.json
xmlhtml2pandas/xmlhtml.pyx
xmlhtml2pandas/xmlhtml_compile.py
xmlhtml2pandas-0.14.dist-info/LICENSE.rst
xmlhtml2pandas-0.14.dist-info/METADATA
xmlhtml2pandas-0.14.dist-info/WHEEL
xmlhtml2pandas-0.14.dist-info/top_level.txt
xmlhtml2pandas-0.14.dist-info/RECORD
