Metadata-Version: 2.1
Name: xmlhtml2pandas
Version: 0.14
Summary: html/ocr parser using Cython/lxml/Tesseract/ImageMagick/Pandas
Home-page: https://github.com/hansalemaos/xmlhtml2pandas
Author: Johannes Fischer
Author-email: aulasparticularesdealemaosp@gmail.com
License: MIT
Keywords: ocr,html
Classifier: Development Status :: 4 - Beta
Classifier: Programming Language :: Python :: 3 :: Only
Classifier: Programming Language :: Python :: 3.10
Classifier: Topic :: Software Development :: Libraries :: Python Modules
Classifier: Topic :: Utilities
License-File: LICENSE.rst
Requires-Dist: Cython
Requires-Dist: exceptdrucker
Requires-Dist: flatten-any-dict-iterable-or-whatsoever
Requires-Dist: lxml
Requires-Dist: numpy
Requires-Dist: pandas
Requires-Dist: setuptools
